mapbox/__init__.py
mapbox/compat.py
mapbox/encoding.py
mapbox/errors.py
mapbox/utils.py
mapbox/services/__init__.py
mapbox/services/analytics.py
mapbox/services/base.py
mapbox/services/datasets.py
mapbox/services/directions.py
mapbox/services/geocoding.py
mapbox/services/mapmatching.py
mapbox/services/maps.py
mapbox/services/matrix.py
mapbox/services/static.py
mapbox/services/static_style.py
mapbox/services/surface.py
mapbox/services/tilequery.py
mapbox/services/uploads.py
mapbox-0.18.1.dist-info/AUTHORS
mapbox-0.18.1.dist-info/LICENSE
mapbox-0.18.1.dist-info/METADATA
mapbox-0.18.1.dist-info/WHEEL
mapbox-0.18.1.dist-info/top_level.txt
mapbox-0.18.1.dist-info/RECORD
