Metadata-Version: 2.1
Name: mapbox
Version: 0.18.1
Summary: A Python client for Mapbox services
Home-page: https://github.com/mapbox/mapbox-sdk-py
Author: Sean Gillies
Author-email: sean@mapbox.com
License: MIT
Classifier: Development Status :: 5 - Production/Stable
Classifier: Environment :: Console
Classifier: Intended Audience :: Developers
Classifier: License :: OSI Approved :: MIT License
Classifier: Programming Language :: Python
Classifier: Programming Language :: Python :: 2.7
Classifier: Programming Language :: Python :: 3
Classifier: Programming Language :: Python :: 3.3
Classifier: Programming Language :: Python :: 3.4
Classifier: Programming Language :: Python :: 3.5
Classifier: Programming Language :: Python :: 3.6
Provides-Extra: test
License-File: LICENSE
License-File: AUTHORS
